LICENSE
MANIFEST.in
requirements.txt
setup.py
python_tuenti.egg-info/PKG-INFO
python_tuenti.egg-info/SOURCES.txt
python_tuenti.egg-info/dependency_links.txt
python_tuenti.egg-info/requires.txt
python_tuenti.egg-info/top_level.txt
tuenti/__init__.py
tuenti/auth.py
tuenti/tuenti.py
tuenti/utils.py