Metadata-Version: 1.1
Name: python-tuenti
Version: 1.1.0
Summary: Wrapper around the latest Tuenti API
Home-page: http://github.com/juanriaza/python-tuenti
Author: Juan Riaza
Author-email: juanriaza@gmail.com
License: BSD
Platform: UNKNOWN
Classifier: Development Status :: 4 - Beta
Classifier: Intended Audience :: Developers
Classifier: License :: OSI Approved :: BSD License
Classifier: Operating System :: OS Independent
Classifier: Programming Language :: Python
Classifier: Topic :: Internet :: WWW/HTTP
